{
    "mood": "cheerful", 
    "caption": "Favorite jacket #4 Montcler ski jacket with retro patches. Music is from The Pink Panther when they're in the ski resort.", 
    "created_at": "2016-05-14T16:22:14-04:00", 
    "file_url": "https://s02.sso.ng/1/00000000002b_19f76daa93fc.ssng", 
    "updated_at": "2016-05-25T11:09:32-04:00", 
    "share_url": "https://a.sso.ng/1/19f76daa93fc", 
    "audio_url": "https://s02.sso.ng/1/00000000002b_19f76daa93fc.m4a", 
    "comment_count": 0, 
    "timeline_image_url": "https://s02.sso.ng/1/00000000002b_19f76daa93fc_mr.jpg", 
    "song_album": "Ultimate Pink Panther", 
    "user": {
        "username": "w", 
        "verified": true, 
        "username_color": null, 
        "full_name": "William", 
        "public_shuttersong": true, 
        "picture_thumb_url": "https://s02.sso.ng/users/0cae3ea0-2922-4a36-9a55-3fc5387033e5.jpg", 
        "id": "0cae3ea0-2922-4a36-9a55-3fc5387033e5"
    }, 
    "song_title": "It Had Better Be Tonight (from the Mirisch-G & e Production \"the Pink Panther\", A United Artists Release)", 
    "is_mine": false, 
    "thumb_url": "https://s02.sso.ng/1/00000000002b_19f76daa93fc_th.jpg", 
    "song_artist": "Henry Mancini and His Orchestra", 
    "favorite_count": 25, 
    "uuid": "1410CD9C-4BE6-4EDF-B675-DFD60BFF767E"
}