{
    "mood": null, 
    "caption": "Pierina hermosa", 
    "created_at": "2015-08-20T20:31:25-04:00", 
    "file_url": "https://s01.sso.ng/1/00000002697a_4cd056759129_1.ssng", 
    "updated_at": "2015-12-27T03:30:47-05:00", 
    "share_url": "https://a.sso.ng/1/4cd056759129", 
    "audio_url": "https://s01.sso.ng/1/00000002697a_4cd056759129_1.m4a", 
    "comment_count": 2, 
    "timeline_image_url": "https://s01.sso.ng/1/00000002697a_4cd056759129_1_mr.jpg", 
    "song_album": "Jar of Hearts - Single", 
    "user": {
        "username": "karynthos", 
        "verified": false, 
        "username_color": null, 
        "full_name": "Karynthos", 
        "public_shuttersong": true, 
        "picture_thumb_url": "https://s02.sso.ng/users/1942f550-b2e9-4a11-88f3-7ae211c95d48.jpg", 
        "id": "1942f550-b2e9-4a11-88f3-7ae211c95d48"
    }, 
    "song_title": "Jar of Hearts", 
    "is_mine": false, 
    "thumb_url": "https://s01.sso.ng/1/00000002697a_4cd056759129_1_th.jpg", 
    "song_artist": "Christina Perri", 
    "favorite_count": 2, 
    "uuid": "1C1B2BEC-E85C-4E3D-A349-16796F3E1B62"
}