{
    "mood": null, 
    "caption": "BEAU SHOULD BE MY VALENTINE #beausvalentine @beaub", 
    "created_at": "2016-02-12T00:19:38-05:00", 
    "file_url": "https://s02.sso.ng/1/00000003e5bc_bae9b47d2cec.ssng", 
    "updated_at": "2016-02-12T02:23:56-05:00", 
    "share_url": "https://a.sso.ng/1/bae9b47d2cec", 
    "audio_url": "https://s02.sso.ng/1/00000003e5bc_bae9b47d2cec.m4a", 
    "comment_count": 0, 
    "timeline_image_url": "https://s02.sso.ng/1/00000003e5bc_bae9b47d2cec_mr.jpg", 
    "song_album": "Would U Love Me - EP", 
    "user": {
        "username": "sassaylube.", 
        "verified": false, 
        "username_color": null, 
        "full_name": "t a y l a h ", 
        "public_shuttersong": true, 
        "picture_thumb_url": "https://s02.sso.ng/users/b1510817-de16-431a-917e-400dca39e5bd.jpg", 
        "id": "b1510817-de16-431a-917e-400dca39e5bd"
    }, 
    "song_title": "Would U Love Me", 
    "is_mine": false, 
    "thumb_url": "https://s02.sso.ng/1/00000003e5bc_bae9b47d2cec_th.jpg", 
    "song_artist": "The Janoskians", 
    "favorite_count": 1, 
    "uuid": "1D5996D0-8BF0-48D0-9EFD-3C9FC8F28FEF"
}