{
    "mood": null, 
    "caption": "? #new #friday", 
    "created_at": "2015-08-21T08:47:35-04:00", 
    "file_url": "https://s01.sso.ng/1/000000028ffa_b11d3db2d828_1.ssng", 
    "updated_at": "2015-08-22T06:36:02-04:00", 
    "share_url": "https://a.sso.ng/1/b11d3db2d828", 
    "audio_url": "https://s01.sso.ng/1/000000028ffa_b11d3db2d828_1.m4a", 
    "comment_count": 0, 
    "timeline_image_url": "https://s01.sso.ng/1/000000028ffa_b11d3db2d828_1_mr.jpg", 
    "song_album": "[Single]", 
    "user": {
        "username": "Msiit", 
        "verified": false, 
        "username_color": null, 
        "full_name": "Miriam", 
        "public_shuttersong": true, 
        "picture_thumb_url": "https://s02.sso.ng/users/17232c9a-abdc-44de-ab36-e7efcb0e6ccb.jpg", 
        "id": "17232c9a-abdc-44de-ab36-e7efcb0e6ccb"
    }, 
    "song_title": "A Drop In The Ocean", 
    "is_mine": false, 
    "thumb_url": "https://s01.sso.ng/1/000000028ffa_b11d3db2d828_1_th.jpg", 
    "song_artist": "Ron Rope", 
    "favorite_count": 1, 
    "uuid": "1498A878-898A-4FB5-994D-E3ACEAF04FEA"
}