{
    "mood": null, 
    "caption": "Love this boy sm ?", 
    "created_at": "2016-03-24T22:58:37-04:00", 
    "file_url": "https://s02.sso.ng/1/00000003e224_d8e10c028389.ssng", 
    "updated_at": "2016-03-24T23:23:28-04:00", 
    "share_url": "https://a.sso.ng/1/d8e10c028389", 
    "audio_url": "https://s02.sso.ng/1/00000003e224_d8e10c028389.m4a", 
    "comment_count": 0, 
    "timeline_image_url": "https://s02.sso.ng/1/00000003e224_d8e10c028389_mr.jpg", 
    "song_album": "Journals", 
    "user": {
        "username": "beausprincesaa", 
        "verified": false, 
        "username_color": null, 
        "full_name": "Princess", 
        "public_shuttersong": true, 
        "picture_thumb_url": "https://s02.sso.ng/users/241fa9dc-2afc-4a07-8ea5-c6340e2c5ba0.jpg", 
        "id": "241fa9dc-2afc-4a07-8ea5-c6340e2c5ba0"
    }, 
    "song_title": "Memphis (feat. Big Sean)", 
    "is_mine": false, 
    "thumb_url": "https://s02.sso.ng/1/00000003e224_d8e10c028389_th.jpg", 
    "song_artist": "Justin Bieber", 
    "favorite_count": 1, 
    "uuid": "132C5D27-C2F6-4981-830D-AC726F3C7654"
}