{
    "mood": null, 
    "caption": "\u2728We're all a little mad here\u2728", 
    "created_at": "2016-06-08T23:03:40-04:00", 
    "file_url": "https://s02.sso.ng/1/000000044d5b_2674e3d3c024.ssng", 
    "updated_at": "2016-06-09T15:45:50-04:00", 
    "share_url": "https://a.sso.ng/1/2674e3d3c024", 
    "audio_url": "https://s02.sso.ng/1/000000044d5b_2674e3d3c024.m4a", 
    "comment_count": 0, 
    "timeline_image_url": "https://s02.sso.ng/1/000000044d5b_2674e3d3c024_mr.jpg", 
    "song_album": "R U Crazy (Radio Edit) - Single", 
    "user": {
        "username": "Lukes_Main_Girl", 
        "verified": false, 
        "username_color": null, 
        "full_name": "Danielle", 
        "public_shuttersong": true, 
        "picture_thumb_url": "https://s02.sso.ng/users/a8f20318-acbe-4444-ac51-7bd705790688.jpg", 
        "id": "a8f20318-acbe-4444-ac51-7bd705790688"
    }, 
    "song_title": "R U Crazy (Radio Edit)", 
    "is_mine": false, 
    "thumb_url": "https://s02.sso.ng/1/000000044d5b_2674e3d3c024_th.jpg", 
    "song_artist": "Conor Maynard", 
    "favorite_count": 2, 
    "uuid": "1DC65092-A7DE-4078-AC98-BA31B0ACA0A0"
}