{
    "mood": null, 
    "caption": "Navidad con mi Mejor Amiga #santasorteo ?????", 
    "created_at": "2015-12-21T15:25:11-05:00", 
    "file_url": "https://s01.sso.ng/1/00000003871d_0791eda82685_1.ssng", 
    "updated_at": "2015-12-22T19:25:33-05:00", 
    "share_url": "https://a.sso.ng/1/0791eda82685", 
    "audio_url": "https://s01.sso.ng/1/00000003871d_0791eda82685_1.m4a", 
    "comment_count": 0, 
    "timeline_image_url": "https://s01.sso.ng/1/00000003871d_0791eda82685_1_mr.jpg", 
    "song_album": "Songs of Innocence", 
    "user": {
        "username": "Made_2903_", 
        "verified": false, 
        "username_color": null, 
        "full_name": null, 
        "public_shuttersong": true, 
        "picture_thumb_url": "https://s02.sso.ng/users/1191b295-5b2b-4736-b6ca-bd0b82c46cf2.jpg", 
        "id": "1191b295-5b2b-4736-b6ca-bd0b82c46cf2"
    }, 
    "song_title": "Volcano", 
    "is_mine": false, 
    "thumb_url": "https://s01.sso.ng/1/00000003871d_0791eda82685_1_th.jpg", 
    "song_artist": "U2", 
    "favorite_count": 1, 
    "uuid": "2C755714-948A-4B62-BC66-5DF2C8C46326"
}