{
    "mood": null, 
    "caption": "#iggyazalea #blackwidow #mywife #myobsession", 
    "created_at": "2015-08-23T00:50:29-04:00", 
    "file_url": "https://s01.sso.ng/1/00000002b849_b877e608320a_1.ssng", 
    "updated_at": "2015-12-25T19:45:30-05:00", 
    "share_url": "https://a.sso.ng/1/b877e608320a", 
    "audio_url": "https://s01.sso.ng/1/00000002b849_b877e608320a_1.m4a", 
    "comment_count": 0, 
    "timeline_image_url": "https://s01.sso.ng/1/00000002b849_b877e608320a_1_mr.jpg", 
    "song_album": "The New Classic", 
    "user": {
        "username": "trejoalberto", 
        "verified": false, 
        "username_color": null, 
        "full_name": null, 
        "public_shuttersong": true, 
        "picture_thumb_url": "https://s02.sso.ng/users/68f797e5-45c3-4d34-9bda-ac617c69f489.jpg", 
        "id": "68f797e5-45c3-4d34-9bda-ac617c69f489"
    }, 
    "song_title": "Black Widow", 
    "is_mine": false, 
    "thumb_url": "https://s01.sso.ng/1/00000002b849_b877e608320a_1_th.jpg", 
    "song_artist": "Iggy Azalea feat. Rita Ora", 
    "favorite_count": 1, 
    "uuid": "2FF123CB-79DB-453F-A542-41104E4E2749"
}