{
    "mood": null, 
    "caption": "Esto fue en Cheltenham,Inglaterra hace 1 a\u00f1o??? #SantaSorteo @abbibrondon", 
    "created_at": "2015-12-23T13:56:01-05:00", 
    "file_url": "https://s01.sso.ng/1/00000003843e_d899a1c8fef4_1.ssng", 
    "updated_at": "2015-12-29T18:40:40-05:00", 
    "share_url": "https://a.sso.ng/1/d899a1c8fef4", 
    "audio_url": "https://s01.sso.ng/1/00000003843e_d899a1c8fef4_1.m4a", 
    "comment_count": 0, 
    "timeline_image_url": "https://s01.sso.ng/1/00000003843e_d899a1c8fef4_1_mr.jpg", 
    "song_album": "Purpose (Deluxe Edition)", 
    "user": {
        "username": "abbibrondon13", 
        "verified": false, 
        "username_color": null, 
        "full_name": "Abbib Rond\u00f3n", 
        "public_shuttersong": true, 
        "picture_thumb_url": "https://s02.sso.ng/users/d7a26797-6e51-46c2-a493-7407458bfd89.jpg", 
        "id": "d7a26797-6e51-46c2-a493-7407458bfd89"
    }, 
    "song_title": "Love Yourself", 
    "is_mine": false, 
    "thumb_url": "https://s01.sso.ng/1/00000003843e_d899a1c8fef4_1_th.jpg", 
    "song_artist": "Justin Bieber", 
    "favorite_count": 4, 
    "uuid": "2BF0160E-75BD-45E7-A690-22DE70FB83ED"
}