{
    "mood": null, 
    "caption": "#SantaSorteo    ???    mari.noguera06@hotmail.com", 
    "created_at": "2015-12-29T18:33:08-05:00", 
    "file_url": "https://s01.sso.ng/1/00000003ade3_d5bc5b6bbcc1.ssng", 
    "updated_at": "2015-12-29T22:41:40-05:00", 
    "share_url": "https://a.sso.ng/1/d5bc5b6bbcc1", 
    "audio_url": "https://s01.sso.ng/1/00000003ade3_d5bc5b6bbcc1.m4a", 
    "comment_count": 0, 
    "timeline_image_url": "https://s01.sso.ng/1/00000003ade3_d5bc5b6bbcc1_mr.jpg", 
    "song_album": "", 
    "user": {
        "username": "nogueramary_", 
        "verified": false, 
        "username_color": null, 
        "full_name": null, 
        "public_shuttersong": true, 
        "picture_thumb_url": "https://s02.sso.ng/users/1c4e61e1-b488-4218-b993-9b281dd01d53.jpg", 
        "id": "1c4e61e1-b488-4218-b993-9b281dd01d53"
    }, 
    "song_title": "Imagine Dragons - Radioactive", 
    "is_mine": false, 
    "thumb_url": "https://s01.sso.ng/1/00000003ade3_d5bc5b6bbcc1_th.jpg", 
    "song_artist": "", 
    "favorite_count": 1, 
    "uuid": "3EE7DB8B-F915-4092-A6FA-8A66B3B739EE"
}