{
    "mood": null, 
    "caption": "You all that matters to me ?", 
    "created_at": "2015-08-21T22:49:18-04:00", 
    "file_url": "https://s01.sso.ng/1/000000028125_ac0b4edc423b_1.ssng", 
    "updated_at": "2015-08-22T15:43:50-04:00", 
    "share_url": "https://a.sso.ng/1/ac0b4edc423b", 
    "audio_url": "https://s01.sso.ng/1/000000028125_ac0b4edc423b_1.m4a", 
    "comment_count": 0, 
    "timeline_image_url": "https://s01.sso.ng/1/000000028125_ac0b4edc423b_1_mr.jpg", 
    "song_album": "Journals", 
    "user": {
        "username": "DannyGlez", 
        "verified": false, 
        "username_color": null, 
        "full_name": null, 
        "public_shuttersong": true, 
        "picture_thumb_url": "https://s02.sso.ng/users/bd154bd6-5087-40db-84a7-5fff317d7cc4.jpg", 
        "id": "bd154bd6-5087-40db-84a7-5fff317d7cc4"
    }, 
    "song_title": "All That Matters", 
    "is_mine": false, 
    "thumb_url": "https://s01.sso.ng/1/000000028125_ac0b4edc423b_1_th.jpg", 
    "song_artist": "Justin Bieber", 
    "favorite_count": 1, 
    "uuid": "40D0B347-8C78-4509-84F9-97CFD9D17F55"
}