{
    "mood": "amused", 
    "caption": "Dunkin Donuts in Iceland offers this highly ironic donut. #Iceland #dd", 
    "created_at": "2016-02-26T18:34:24-05:00", 
    "file_url": "https://s02.sso.ng/1/00000000002b_7f23694ae9e7.ssng", 
    "updated_at": "2016-03-26T05:51:15-04:00", 
    "share_url": "https://a.sso.ng/1/7f23694ae9e7", 
    "audio_url": "https://s02.sso.ng/1/00000000002b_7f23694ae9e7.m4a", 
    "comment_count": 2, 
    "timeline_image_url": "https://s02.sso.ng/1/00000000002b_7f23694ae9e7_mr.jpg", 
    "song_album": "Oh My Gosh", 
    "user": {
        "username": "w", 
        "verified": true, 
        "username_color": null, 
        "full_name": "William", 
        "public_shuttersong": true, 
        "picture_thumb_url": "https://s02.sso.ng/users/0cae3ea0-2922-4a36-9a55-3fc5387033e5.jpg", 
        "id": "0cae3ea0-2922-4a36-9a55-3fc5387033e5"
    }, 
    "song_title": "Oh My Gosh (Jaxx Club edit)", 
    "is_mine": false, 
    "thumb_url": "https://s02.sso.ng/1/00000000002b_7f23694ae9e7_th.jpg", 
    "song_artist": "Basement Jaxx", 
    "favorite_count": 33, 
    "uuid": "4B7F5907-B585-4D5A-97CC-6C1E5C2CF17F"
}