{
    "mood": null, 
    "caption": "Do you like foster the people? ? @jackjackjohnson @jackjohnsonofficial @jackgilinskyofficial @jackgilinsky", 
    "created_at": "2015-08-04T13:43:01-04:00", 
    "file_url": "https://s01.sso.ng/1/000000020db9_d2dfff1cb32c_1.ssng", 
    "updated_at": "2015-08-04T13:44:07-04:00", 
    "share_url": "https://a.sso.ng/1/d2dfff1cb32c", 
    "audio_url": "https://s01.sso.ng/1/000000020db9_d2dfff1cb32c_1.m4a", 
    "comment_count": 0, 
    "timeline_image_url": "https://s01.sso.ng/1/000000020db9_d2dfff1cb32c_1_mr.jpg", 
    "song_album": "", 
    "user": {
        "username": "1Dkareen", 
        "verified": false, 
        "username_color": null, 
        "full_name": "Karen", 
        "public_shuttersong": true, 
        "picture_thumb_url": "https://s02.sso.ng/users/dfc32c3f-8666-47f2-ad23-83e13979c524.jpg", 
        "id": "dfc32c3f-8666-47f2-ad23-83e13979c524"
    }, 
    "song_title": "Houdini", 
    "is_mine": false, 
    "thumb_url": "https://s01.sso.ng/1/000000020db9_d2dfff1cb32c_1_th.jpg", 
    "song_artist": "Foster the people", 
    "favorite_count": 2, 
    "uuid": "5A044519-7BD6-4628-BC6B-0B4A52B89402"
}