{
    "mood": null, 
    "caption": "", 
    "created_at": "2015-12-19T10:51:50-05:00", 
    "file_url": "https://s01.sso.ng/1/000000036e23_0352813bd7a4.ssng", 
    "updated_at": "2015-12-24T08:58:20-05:00", 
    "share_url": "https://a.sso.ng/1/0352813bd7a4", 
    "audio_url": "https://s01.sso.ng/1/000000036e23_0352813bd7a4.m4a", 
    "comment_count": 0, 
    "timeline_image_url": "https://s01.sso.ng/1/000000036e23_0352813bd7a4_mr.jpg", 
    "song_album": "", 
    "user": {
        "username": "angelestrella", 
        "verified": false, 
        "username_color": null, 
        "full_name": null, 
        "public_shuttersong": true, 
        "picture_thumb_url": "https://s02.sso.ng/users/369af7f2-7a31-47fe-97ab-1339101cf789.jpg", 
        "id": "369af7f2-7a31-47fe-97ab-1339101cf789"
    }, 
    "song_title": "Silento Watch Me (Whip_ Nae Nae)", 
    "is_mine": false, 
    "thumb_url": "https://s01.sso.ng/1/000000036e23_0352813bd7a4_th.jpg", 
    "song_artist": "", 
    "favorite_count": 1, 
    "uuid": "5C08316D-5518-4727-BD0C-64E4AC8ECAA9"
}