{
    "mood": null, 
    "caption": "#SantaSorteo YouTube: Stephany B. Daza", 
    "created_at": "2015-12-26T16:51:32-05:00", 
    "file_url": "https://s01.sso.ng/1/000000027409_49933838ff61.ssng", 
    "updated_at": "2015-12-26T17:04:39-05:00", 
    "share_url": "https://a.sso.ng/1/49933838ff61", 
    "audio_url": "https://s01.sso.ng/1/000000027409_49933838ff61.m4a", 
    "comment_count": 0, 
    "timeline_image_url": "https://s01.sso.ng/1/000000027409_49933838ff61_mr.jpg", 
    "song_album": "", 
    "user": {
        "username": "stephanybd", 
        "verified": false, 
        "username_color": null, 
        "full_name": "Stephany", 
        "public_shuttersong": true, 
        "picture_thumb_url": "https://s02.sso.ng/users/c416df43-643c-42b8-b6fe-1fe871ed4a8f.jpg", 
        "id": "c416df43-643c-42b8-b6fe-1fe871ed4a8f"
    }, 
    "song_title": "Jingle Bells", 
    "is_mine": false, 
    "thumb_url": "https://s01.sso.ng/1/000000027409_49933838ff61_th.jpg", 
    "song_artist": "", 
    "favorite_count": 1, 
    "uuid": "6602EFE0-6DB5-4665-AE75-BBDD67E754F8"
}