{
    "mood": "contento", 
    "caption": "Es s\u00faper lindo \u263a\ufe0f???\u2764\ufe0f #SantaSorteo YouTube: Paola Mendoza (Por si acaso) paolamendoza434@gmail.com", 
    "created_at": "2015-12-21T21:15:16-05:00", 
    "file_url": "https://s01.sso.ng/1/000000037776_e45f76bd12d3_1.ssng", 
    "updated_at": "2015-12-25T23:22:40-05:00", 
    "share_url": "https://a.sso.ng/1/e45f76bd12d3", 
    "audio_url": "https://s01.sso.ng/1/000000037776_e45f76bd12d3_1.m4a", 
    "comment_count": 0, 
    "timeline_image_url": "https://s01.sso.ng/1/000000037776_e45f76bd12d3_1_mr.jpg", 
    "song_album": "Good For You", 
    "user": {
        "username": "PaolaVMendoza", 
        "verified": false, 
        "username_color": null, 
        "full_name": null, 
        "public_shuttersong": true, 
        "picture_thumb_url": "https://s02.sso.ng/users/11f3aca3-e347-4dda-8989-68eb7b41de5f.jpg", 
        "id": "11f3aca3-e347-4dda-8989-68eb7b41de5f"
    }, 
    "song_title": "Selena Gomez - Good For You", 
    "is_mine": false, 
    "thumb_url": "https://s01.sso.ng/1/000000037776_e45f76bd12d3_1_th.jpg", 
    "song_artist": "Selena Gomez", 
    "favorite_count": 3, 
    "uuid": "72AFC681-6CB4-43DE-A5A5-278741E98852"
}