{
    "mood": null, 
    "caption": "Haven't meet u guys yet but I'm not going to stop until I do everyday my love for u guys grows even more and more love u guys @jackandjackofficial", 
    "created_at": "2015-12-12T00:06:45-05:00", 
    "file_url": "https://s01.sso.ng/1/000000022dc4_472dc5360e0e_1.ssng", 
    "updated_at": "2015-12-12T15:34:43-05:00", 
    "share_url": "https://a.sso.ng/1/472dc5360e0e", 
    "audio_url": "https://s01.sso.ng/1/000000022dc4_472dc5360e0e_1.m4a", 
    "comment_count": 1, 
    "timeline_image_url": "https://s01.sso.ng/1/000000022dc4_472dc5360e0e_1_mr.jpg", 
    "song_album": "The 20/20 Experience", 
    "user": {
        "username": "maritzaonly1", 
        "verified": false, 
        "username_color": null, 
        "full_name": null, 
        "public_shuttersong": true, 
        "picture_thumb_url": "https://s02.sso.ng/users/77852b78-8e21-45d8-baef-a9b0c1457512.jpg", 
        "id": "77852b78-8e21-45d8-baef-a9b0c1457512"
    }, 
    "song_title": "Mirrors", 
    "is_mine": false, 
    "thumb_url": "https://s01.sso.ng/1/000000022dc4_472dc5360e0e_1_th.jpg", 
    "song_artist": "Justin Timberlake", 
    "favorite_count": 1, 
    "uuid": "7B72E1AE-881D-4A6E-BAB1-D907DACBA957"
}