{
    "mood": null, 
    "caption": "#SantaSorteo Youtube: Andrea Fuentes", 
    "created_at": "2015-12-23T23:44:49-05:00", 
    "file_url": "https://s01.sso.ng/1/00000003669a_eec6b40de6dc.ssng", 
    "updated_at": "2015-12-24T00:20:45-05:00", 
    "share_url": "https://a.sso.ng/1/eec6b40de6dc", 
    "audio_url": "https://s01.sso.ng/1/00000003669a_eec6b40de6dc.m4a", 
    "comment_count": 0, 
    "timeline_image_url": "https://s01.sso.ng/1/00000003669a_eec6b40de6dc_mr.jpg", 
    "song_album": "Songs of Innocence", 
    "user": {
        "username": "Anndrea_Fuentes", 
        "verified": false, 
        "username_color": null, 
        "full_name": "Andrea Fuentes.", 
        "public_shuttersong": true, 
        "picture_thumb_url": "https://s02.sso.ng/users/a8200bdb-cf35-4ce9-b059-d674b290c5f8.jpg", 
        "id": "a8200bdb-cf35-4ce9-b059-d674b290c5f8"
    }, 
    "song_title": "This Is Where You Can Reach Me Now", 
    "is_mine": false, 
    "thumb_url": "https://s01.sso.ng/1/00000003669a_eec6b40de6dc_th.jpg", 
    "song_artist": "U2", 
    "favorite_count": 2, 
    "uuid": "7258B2F3-1AC3-476C-B74A-7040FE2849FF"
}