{
    "mood": "affectionate", 
    "caption": "#beausvaletine I miss you beau PLESE come to England soon xx love you beau", 
    "created_at": "2016-02-12T01:52:56-05:00", 
    "file_url": "https://s02.sso.ng/1/00000003e2c9_ed59ba92de16.ssng", 
    "updated_at": "2016-02-12T10:17:02-05:00", 
    "share_url": "https://a.sso.ng/1/ed59ba92de16", 
    "audio_url": "https://s02.sso.ng/1/00000003e2c9_ed59ba92de16.m4a", 
    "comment_count": 0, 
    "timeline_image_url": "https://s02.sso.ng/1/00000003e2c9_ed59ba92de16_mr.jpg", 
    "song_album": "BEYONC\u00c9", 
    "user": {
        "username": "misslukebrooks", 
        "verified": false, 
        "username_color": null, 
        "full_name": "Larissa Brooks", 
        "public_shuttersong": true, 
        "picture_thumb_url": "https://s02.sso.ng/users/a39b87e7-84e2-4c75-b5b0-c395e17dbd00.jpg", 
        "id": "a39b87e7-84e2-4c75-b5b0-c395e17dbd00"
    }, 
    "song_title": "XO", 
    "is_mine": false, 
    "thumb_url": "https://s02.sso.ng/1/00000003e2c9_ed59ba92de16_th.jpg", 
    "song_artist": "Beyonc\u00e9", 
    "favorite_count": 2, 
    "uuid": "877DD72E-ADB4-41ED-8C63-F72D7326AC99"
}