{
    "mood": null, 
    "caption": "", 
    "created_at": "2016-04-18T07:33:17-04:00", 
    "file_url": "https://s02.sso.ng/1/00000003eed8_8b3e4113bbc9.ssng", 
    "updated_at": "2016-04-19T12:56:59-04:00", 
    "share_url": "https://a.sso.ng/1/8b3e4113bbc9", 
    "audio_url": "https://s02.sso.ng/1/00000003eed8_8b3e4113bbc9.m4a", 
    "comment_count": 0, 
    "timeline_image_url": "https://s02.sso.ng/1/00000003eed8_8b3e4113bbc9_mr.jpg", 
    "song_album": "Tutto finir\u00e0 bene", 
    "user": {
        "username": "Dani_Blastema", 
        "verified": false, 
        "username_color": null, 
        "full_name": null, 
        "public_shuttersong": true, 
        "picture_thumb_url": "https://s02.sso.ng/users/866026a9-388f-41c8-84d2-555afc6c39f2.jpg", 
        "id": "866026a9-388f-41c8-84d2-555afc6c39f2"
    }, 
    "song_title": "Asteroide", 
    "is_mine": false, 
    "thumb_url": "https://s02.sso.ng/1/00000003eed8_8b3e4113bbc9_th.jpg", 
    "song_artist": "Blastema", 
    "favorite_count": 2, 
    "uuid": "96EB37DE-0703-4A1E-9846-C462A6C7024E"
}