{
    "mood": null, 
    "caption": "School", 
    "created_at": "2015-08-22T14:53:22-04:00", 
    "file_url": "https://s01.sso.ng/1/00000002a775_2f79c8490178_1.ssng", 
    "updated_at": "2015-08-22T23:45:14-04:00", 
    "share_url": "https://a.sso.ng/1/2f79c8490178", 
    "audio_url": "https://s01.sso.ng/1/00000002a775_2f79c8490178_1.m4a", 
    "comment_count": 2, 
    "timeline_image_url": "https://s01.sso.ng/1/00000002a775_2f79c8490178_1_mr.jpg", 
    "song_album": "Le Troublant Acid - Single", 
    "user": {
        "username": "annagil", 
        "verified": false, 
        "username_color": null, 
        "full_name": null, 
        "public_shuttersong": true, 
        "picture_thumb_url": "https://s02.sso.ng/users/c3b22561-0a67-43f8-b1c4-5f19734476ef.jpg", 
        "id": "c3b22561-0a67-43f8-b1c4-5f19734476ef"
    }, 
    "song_title": "Le Troublant Acid", 
    "is_mine": false, 
    "thumb_url": "https://s01.sso.ng/1/00000002a775_2f79c8490178_1_th.jpg", 
    "song_artist": "KZA", 
    "favorite_count": 6, 
    "uuid": "97C15867-7910-467C-81CE-521206FB13B8"
}