{
    "mood": null, 
    "caption": "@brooksluke u ever gonna follow me??", 
    "created_at": "2016-02-11T10:51:10-05:00", 
    "file_url": "https://s02.sso.ng/1/00000003e443_2936ab19023f.ssng", 
    "updated_at": "2016-02-13T05:14:14-05:00", 
    "share_url": "https://a.sso.ng/1/2936ab19023f", 
    "audio_url": "https://s02.sso.ng/1/00000003e443_2936ab19023f.m4a", 
    "comment_count": 0, 
    "timeline_image_url": "https://s02.sso.ng/1/00000003e443_2936ab19023f_mr.jpg", 
    "song_album": "Best Friends", 
    "user": {
        "username": "handsonmeluke", 
        "verified": false, 
        "username_color": null, 
        "full_name": "jack", 
        "public_shuttersong": true, 
        "picture_thumb_url": "https://s02.sso.ng/users/068d559b-a578-43c1-8149-56aed1519d98.jpg", 
        "id": "068d559b-a578-43c1-8149-56aed1519d98"
    }, 
    "song_title": "Best Friends", 
    "is_mine": false, 
    "thumb_url": "https://s02.sso.ng/1/00000003e443_2936ab19023f_th.jpg", 
    "song_artist": "The Janoskians", 
    "favorite_count": 3, 
    "uuid": "963FA6E7-5DC6-46AA-9503-F0D5DC7069C0"
}