{
    "mood": null, 
    "caption": "", 
    "created_at": "2015-08-21T11:24:12-04:00", 
    "file_url": "https://s01.sso.ng/1/000000027ad0_683c7395ed6d.ssng", 
    "updated_at": "2015-08-21T21:21:23-04:00", 
    "share_url": "https://a.sso.ng/1/683c7395ed6d", 
    "audio_url": "https://s01.sso.ng/1/000000027ad0_683c7395ed6d.m4a", 
    "comment_count": 0, 
    "timeline_image_url": "https://s01.sso.ng/1/000000027ad0_683c7395ed6d_mr.jpg", 
    "song_album": "", 
    "user": {
        "username": "vicky123", 
        "verified": false, 
        "username_color": null, 
        "full_name": null, 
        "public_shuttersong": true, 
        "picture_thumb_url": "https://s02.sso.ng/users/72ec95c1-5687-42e0-bab1-6b4acaf73cf5.jpg", 
        "id": "72ec95c1-5687-42e0-bab1-6b4acaf73cf5"
    }, 
    "song_title": "Demi Lovato - Cool for the Summer (Official Video)", 
    "is_mine": false, 
    "thumb_url": "https://s01.sso.ng/1/000000027ad0_683c7395ed6d_th.jpg", 
    "song_artist": "", 
    "favorite_count": 1, 
    "uuid": "A5975BB9-DFD1-47CF-BB1B-6B66F7192904"
}