{
    "mood": null, 
    "caption": "soy culpable lo acepto ??? #santasorteo youtube isabel montoya  isabel.9507@gmail.com", 
    "created_at": "2015-12-30T14:10:09-05:00", 
    "file_url": "https://s01.sso.ng/1/000000032253_871c5e60dfaa.ssng", 
    "updated_at": "2015-12-30T21:09:13-05:00", 
    "share_url": "https://a.sso.ng/1/871c5e60dfaa", 
    "audio_url": "https://s01.sso.ng/1/000000032253_871c5e60dfaa.m4a", 
    "comment_count": 0, 
    "timeline_image_url": "https://s01.sso.ng/1/000000032253_871c5e60dfaa_mr.jpg", 
    "song_album": "", 
    "user": {
        "username": "isabelmontoyah", 
        "verified": false, 
        "username_color": null, 
        "full_name": "isabel cristina montoya hernandez", 
        "public_shuttersong": true, 
        "picture_thumb_url": "https://s02.sso.ng/users/d0129d79-36aa-41e5-9bfd-c4bc1cbf6e5e.jpg", 
        "id": "d0129d79-36aa-41e5-9bfd-c4bc1cbf6e5e"
    }, 
    "song_title": "A92C65A8-E722-4430-85B5-C8C6F8D83E32", 
    "is_mine": false, 
    "thumb_url": "https://s01.sso.ng/1/000000032253_871c5e60dfaa_th.jpg", 
    "song_artist": "", 
    "favorite_count": 1, 
    "uuid": "A7BE2706-5CA7-414A-92DB-37670272A529"
}