{
    "mood": "", 
    "caption": "", 
    "created_at": "2016-02-01T04:40:27-05:00", 
    "file_url": "https://s02.sso.ng/1/000000000119_8060c4360262.ssng", 
    "updated_at": "2016-02-01T05:07:22-05:00", 
    "share_url": "https://a.sso.ng/1/8060c4360262", 
    "audio_url": "https://s02.sso.ng/1/000000000119_8060c4360262.m4a", 
    "comment_count": 2, 
    "timeline_image_url": "https://s02.sso.ng/1/000000000119_8060c4360262_mr.jpg", 
    "song_album": "", 
    "user": {
        "username": "yonanda.w", 
        "verified": false, 
        "username_color": "#F95E59", 
        "full_name": "Yonanda W", 
        "public_shuttersong": true, 
        "picture_thumb_url": "https://s02.sso.ng/users/f4089cb7-39f4-460e-b992-01338c1b1feb.jpg", 
        "id": "f4089cb7-39f4-460e-b992-01338c1b1feb"
    }, 
    "song_title": "Taylor Swift - We Are Never Ever Getting Back Together", 
    "is_mine": false, 
    "thumb_url": "https://s02.sso.ng/1/000000000119_8060c4360262_th.jpg", 
    "song_artist": "", 
    "favorite_count": 1, 
    "uuid": "A6965102-003B-420A-AA93-523C10A88C13"
}