{
    "mood": "depressed", 
    "caption": "Wish @beaub and @brooksluke would follow me :(", 
    "created_at": "2016-02-18T18:24:20-05:00", 
    "file_url": "https://s02.sso.ng/1/00000003e1ee_3e664ce49b6b.ssng", 
    "updated_at": "2016-02-23T17:32:37-05:00", 
    "share_url": "https://a.sso.ng/1/3e664ce49b6b", 
    "audio_url": "https://s02.sso.ng/1/00000003e1ee_3e664ce49b6b.m4a", 
    "comment_count": 0, 
    "timeline_image_url": "https://s02.sso.ng/1/00000003e1ee_3e664ce49b6b_mr.jpg", 
    "song_album": "Calibraska - EP", 
    "user": {
        "username": "High5Forever", 
        "verified": false, 
        "username_color": null, 
        "full_name": null, 
        "public_shuttersong": true, 
        "picture_thumb_url": "https://s02.sso.ng/users/4edc5e55-f2d9-4257-9cdb-e14b16d99009.jpg", 
        "id": "4edc5e55-f2d9-4257-9cdb-e14b16d99009"
    }, 
    "song_title": "Wrong One", 
    "is_mine": false, 
    "thumb_url": "https://s02.sso.ng/1/00000003e1ee_3e664ce49b6b_th.jpg", 
    "song_artist": "Jack & Jack", 
    "favorite_count": 5, 
    "uuid": "B9A04DB9-2DE9-47DD-A305-182A0B2D85FF"
}