{
    "mood": null, 
    "caption": "You can do anything you put your mind to! Listen to Jack & Jack on AppleMusic. https://itun.es/us/VUUr4", 
    "created_at": "2015-08-01T15:13:00-04:00", 
    "file_url": "https://s01.sso.ng/1/000000020144_a94fee002f1b.ssng", 
    "updated_at": "2016-05-31T20:56:45-04:00", 
    "share_url": "https://a.sso.ng/1/a94fee002f1b", 
    "audio_url": "https://s01.sso.ng/1/000000020144_a94fee002f1b.m4a", 
    "comment_count": 171, 
    "timeline_image_url": "https://s01.sso.ng/1/000000020144_a94fee002f1b_mr.jpg", 
    "song_album": "Calibraska - EP", 
    "user": {
        "username": "JackGilinskyOfficial", 
        "verified": true, 
        "username_color": null, 
        "full_name": null, 
        "public_shuttersong": true, 
        "picture_thumb_url": "https://s02.sso.ng/users/694e24ea-5960-4343-be67-c50fce6b64ae.jpg", 
        "id": "694e24ea-5960-4343-be67-c50fce6b64ae"
    }, 
    "song_title": "California", 
    "is_mine": false, 
    "thumb_url": "https://s01.sso.ng/1/000000020144_a94fee002f1b_th.jpg", 
    "song_artist": "Jack & Jack", 
    "favorite_count": 641, 
    "uuid": "BA73285D-1ACA-4875-A71E-8DA8EC1CFFE5"
}