{
    "mood": null, 
    "caption": "#SantaSorteo YouTube: Alex Wayland \u2603", 
    "created_at": "2015-12-20T21:32:03-05:00", 
    "file_url": "https://s01.sso.ng/1/000000037a0a_712c424e4b5f_1.ssng", 
    "updated_at": "2015-12-25T21:06:31-05:00", 
    "share_url": "https://a.sso.ng/1/712c424e4b5f", 
    "audio_url": "https://s01.sso.ng/1/000000037a0a_712c424e4b5f_1.m4a", 
    "comment_count": 0, 
    "timeline_image_url": "https://s01.sso.ng/1/000000037a0a_712c424e4b5f_1_mr.jpg", 
    "song_album": "Cry Baby (Deluxe Version)", 
    "user": {
        "username": "AlexVaz", 
        "verified": false, 
        "username_color": null, 
        "full_name": null, 
        "public_shuttersong": true, 
        "picture_thumb_url": "https://s02.sso.ng/users/98722ee6-a2c4-47db-b6f3-97bf0e3232cc.jpg", 
        "id": "98722ee6-a2c4-47db-b6f3-97bf0e3232cc"
    }, 
    "song_title": "Play Date", 
    "is_mine": false, 
    "thumb_url": "https://s01.sso.ng/1/000000037a0a_712c424e4b5f_1_th.jpg", 
    "song_artist": "Melanie Martinez", 
    "favorite_count": 1, 
    "uuid": "B1F37DC1-C9E3-4235-B4E7-AA018DC57964"
}