{
    "mood": null, 
    "caption": "@beaub I took this photo of you at #JahooJahaaTour \u2764\ufe0f", 
    "created_at": "2016-02-09T18:11:35-05:00", 
    "file_url": "https://s02.sso.ng/1/00000003e3a2_ba1366f8696d.ssng", 
    "updated_at": "2016-03-29T14:36:43-04:00", 
    "share_url": "https://a.sso.ng/1/ba1366f8696d", 
    "audio_url": "https://s02.sso.ng/1/00000003e3a2_ba1366f8696d.m4a", 
    "comment_count": 0, 
    "timeline_image_url": "https://s02.sso.ng/1/00000003e3a2_ba1366f8696d_mr.jpg", 
    "song_album": "Would U Love Me - EP", 
    "user": {
        "username": "slutnoskiansss", 
        "verified": false, 
        "username_color": null, 
        "full_name": "Liv ", 
        "public_shuttersong": true, 
        "picture_thumb_url": "https://s02.sso.ng/users/78816524-f5b8-4391-a145-5c11cf19557c.jpg", 
        "id": "78816524-f5b8-4391-a145-5c11cf19557c"
    }, 
    "song_title": "MoodSwings", 
    "is_mine": false, 
    "thumb_url": "https://s02.sso.ng/1/00000003e3a2_ba1366f8696d_th.jpg", 
    "song_artist": "The Janoskians", 
    "favorite_count": 5, 
    "uuid": "C4CAD48A-A3D3-4FD3-B3AC-B6A6A41E7733"
}