{
    "mood": null, 
    "caption": "I miss Eli so much? But I know I'll see him next year? He'll finally be 8, such a big boy now????", 
    "created_at": "2015-08-05T17:14:41-04:00", 
    "file_url": "https://s01.sso.ng/1/000000020a99_6af5c899f89c_1.ssng", 
    "updated_at": "2015-08-05T17:16:09-04:00", 
    "share_url": "https://a.sso.ng/1/6af5c899f89c", 
    "audio_url": "https://s01.sso.ng/1/000000020a99_6af5c899f89c_1.m4a", 
    "comment_count": 0, 
    "timeline_image_url": "https://s01.sso.ng/1/000000020a99_6af5c899f89c_1_mr.jpg", 
    "song_album": "Groove - Single", 
    "user": {
        "username": "miafuentes", 
        "verified": false, 
        "username_color": null, 
        "full_name": "Mia Fuentes", 
        "public_shuttersong": true, 
        "picture_thumb_url": "https://s02.sso.ng/users/685f6408-dabc-474d-b52f-fba0ed706b1e.jpg", 
        "id": "685f6408-dabc-474d-b52f-fba0ed706b1e"
    }, 
    "song_title": "Groove", 
    "is_mine": false, 
    "thumb_url": "https://s01.sso.ng/1/000000020a99_6af5c899f89c_1_th.jpg", 
    "song_artist": "Jack & Jack", 
    "favorite_count": 1, 
    "uuid": "CC965698-76CE-4ACA-A46B-8325F1C2713D"
}