{
    "mood": null, 
    "caption": "", 
    "created_at": "2016-05-19T09:18:31-04:00", 
    "file_url": "https://s02.sso.ng/1/000000042d76_dcad35a366ee.ssng", 
    "updated_at": "2016-05-20T16:21:56-04:00", 
    "share_url": "https://a.sso.ng/1/dcad35a366ee", 
    "audio_url": "https://s02.sso.ng/1/000000042d76_dcad35a366ee.m4a", 
    "comment_count": 0, 
    "timeline_image_url": "https://s02.sso.ng/1/000000042d76_dcad35a366ee_mr.jpg", 
    "song_album": "E. 1999 Eternal", 
    "user": {
        "username": "chronic_motiv", 
        "verified": false, 
        "username_color": null, 
        "full_name": null, 
        "public_shuttersong": true, 
        "picture_thumb_url": "https://s02.sso.ng/users/", 
        "id": "06fcf7c2-9f92-49da-9eba-c27ff81bbd21"
    }, 
    "song_title": "Tha Crossroads", 
    "is_mine": false, 
    "thumb_url": "https://s02.sso.ng/1/000000042d76_dcad35a366ee_th.jpg", 
    "song_artist": "Bone Thugs-n-Harmony", 
    "favorite_count": 3, 
    "uuid": "CF320FE7-027C-4207-80E9-78855A28781A"
}