{
    "mood": null, 
    "caption": "#SantaSorteo \nHolo???\nYoutube: alma Leticia vivero a Hern\u00e1ndez \nLa cuenta ??? es mia solo que tiene otro nombre \nCorreo electr\u00f3nico: letyviveros@itesm.mx", 
    "created_at": "2015-12-26T21:14:20-05:00", 
    "file_url": "https://s01.sso.ng/1/00000003959f_2c74122bb25a.ssng", 
    "updated_at": "2015-12-28T17:51:09-05:00", 
    "share_url": "https://a.sso.ng/1/2c74122bb25a", 
    "audio_url": "https://s01.sso.ng/1/00000003959f_2c74122bb25a.m4a", 
    "comment_count": 0, 
    "timeline_image_url": "https://s01.sso.ng/1/00000003959f_2c74122bb25a_mr.jpg", 
    "song_album": "Metallica", 
    "user": {
        "username": "brianchavez", 
        "verified": false, 
        "username_color": null, 
        "full_name": "", 
        "public_shuttersong": true, 
        "picture_thumb_url": "https://s02.sso.ng/users/fcd476fa-4138-47ec-a6c4-b98fabc04b2f.jpg", 
        "id": "fcd476fa-4138-47ec-a6c4-b98fabc04b2f"
    }, 
    "song_title": "Am I Evil?", 
    "is_mine": false, 
    "thumb_url": "https://s01.sso.ng/1/00000003959f_2c74122bb25a_th.jpg", 
    "song_artist": "Creeping Death", 
    "favorite_count": 3, 
    "uuid": "D1D34E2C-AEDB-4405-81CB-7D02206A9EC6"
}