{
    "mood": null, 
    "caption": "Every day of summer seems to have a great #throwback ? This was exactly 2 years ago in Tel Aviv, Israel...I guess the poor English weather is kind of offset by how easy it is to travel", 
    "created_at": "2015-07-26T10:34:50-04:00", 
    "file_url": "https://s01.sso.ng/1/000000000045_34a3a103c2a0_1.ssng", 
    "updated_at": "2015-12-29T18:21:18-05:00", 
    "share_url": "https://a.sso.ng/1/34a3a103c2a0", 
    "audio_url": "https://s01.sso.ng/1/000000000045_34a3a103c2a0_1.m4a", 
    "comment_count": 2, 
    "timeline_image_url": "https://s01.sso.ng/1/000000000045_34a3a103c2a0_1_mr.jpg", 
    "song_album": "The Annual 2015 - Ministry of Sound", 
    "user": {
        "username": "go", 
        "verified": true, 
        "username_color": "#f2766a", 
        "full_name": "Georgina Oxford", 
        "public_shuttersong": true, 
        "picture_thumb_url": "https://s02.sso.ng/users/09b3db81-d909-45ee-b737-9c9283d5caeb.jpg", 
        "id": "09b3db81-d909-45ee-b737-9c9283d5caeb"
    }, 
    "song_title": "Pushing On", 
    "is_mine": false, 
    "thumb_url": "https://s01.sso.ng/1/000000000045_34a3a103c2a0_1_th.jpg", 
    "song_artist": "Oliver $ & Jimi Jules", 
    "favorite_count": 28, 
    "uuid": "D765FE18-BD56-4E7C-B38D-57BD1986EEA2"
}