{
    "mood": "curious", 
    "caption": "why does beaus hat have a tag on it @brooksluke @beaub ???", 
    "created_at": "2016-05-11T02:06:40-04:00", 
    "file_url": "https://s02.sso.ng/1/00000003e246_74a56767842e.ssng", 
    "updated_at": "2016-05-15T14:46:36-04:00", 
    "share_url": "https://a.sso.ng/1/74a56767842e", 
    "audio_url": "https://s02.sso.ng/1/00000003e246_74a56767842e.m4a", 
    "comment_count": 0, 
    "timeline_image_url": "https://s02.sso.ng/1/00000003e246_74a56767842e_mr.jpg", 
    "song_album": "All I Want 4 Christmas - Single", 
    "user": {
        "username": "RAINDROPJAI", 
        "verified": false, 
        "username_color": null, 
        "full_name": null, 
        "public_shuttersong": true, 
        "picture_thumb_url": "https://s02.sso.ng/users/65ffb820-9cf2-4cc9-99db-4b3af51a1672.jpg", 
        "id": "65ffb820-9cf2-4cc9-99db-4b3af51a1672"
    }, 
    "song_title": "All I Want 4 Christmas", 
    "is_mine": false, 
    "thumb_url": "https://s02.sso.ng/1/00000003e246_74a56767842e_th.jpg", 
    "song_artist": "The Janoskians", 
    "favorite_count": 14, 
    "uuid": "DC9AC617-7219-4697-9202-9896F0B68DBA"
}