{
    "mood": "", 
    "caption": "", 
    "created_at": "2016-04-27T17:03:41-04:00", 
    "file_url": "https://s02.sso.ng/1/0000000422c0_0bb00ac976fe.ssng", 
    "updated_at": "2016-04-28T00:40:36-04:00", 
    "share_url": "https://a.sso.ng/1/0bb00ac976fe", 
    "audio_url": "https://s02.sso.ng/1/0000000422c0_0bb00ac976fe.m4a", 
    "comment_count": 0, 
    "timeline_image_url": "https://s02.sso.ng/1/0000000422c0_0bb00ac976fe_mr.jpg", 
    "song_album": "Word In The Streets 14", 
    "user": {
        "username": "lyfe101", 
        "verified": false, 
        "username_color": null, 
        "full_name": null, 
        "public_shuttersong": true, 
        "picture_thumb_url": "https://s02.sso.ng/users/", 
        "id": "34e866f4-1635-4f72-a706-dfa452b5e565"
    }, 
    "song_title": "On the Way", 
    "is_mine": false, 
    "thumb_url": "https://s02.sso.ng/1/0000000422c0_0bb00ac976fe_th.jpg", 
    "song_artist": "Big Sean & Jhene' Aiko", 
    "favorite_count": 1, 
    "uuid": "D3DE9CC2-1777-4583-B5BA-D44AA66152D5"
}