{
    "mood": null, 
    "caption": "", 
    "created_at": "2016-02-09T18:50:51-05:00", 
    "file_url": "https://s02.sso.ng/1/00000003e63b_855be3b43e29.ssng", 
    "updated_at": "2016-02-10T13:54:21-05:00", 
    "share_url": "https://a.sso.ng/1/855be3b43e29", 
    "audio_url": "https://s02.sso.ng/1/00000003e63b_855be3b43e29.m4a", 
    "comment_count": 1, 
    "timeline_image_url": "https://s02.sso.ng/1/00000003e63b_855be3b43e29_mr.jpg", 
    "song_album": "Purpose (Deluxe)", 
    "user": {
        "username": "jaydacormick", 
        "verified": false, 
        "username_color": null, 
        "full_name": null, 
        "public_shuttersong": true, 
        "picture_thumb_url": "https://s02.sso.ng/users/fa12e520-8343-4381-a8ad-7c3f9f023b3e.jpg", 
        "id": "fa12e520-8343-4381-a8ad-7c3f9f023b3e"
    }, 
    "song_title": "Purpose", 
    "is_mine": false, 
    "thumb_url": "https://s02.sso.ng/1/00000003e63b_855be3b43e29_th.jpg", 
    "song_artist": "Justin Bieber", 
    "favorite_count": 1, 
    "uuid": "D383099C-5C39-451A-99F8-33410D84E3C7"
}