{
    "mood": null, 
    "caption": "\"I'll be thinking of you and only you. Worldwide. No matter what.\" I love you to the stars and beyond. \ud83d\udc99", 
    "created_at": "2016-06-03T15:24:56-04:00", 
    "file_url": "https://s02.sso.ng/1/000000043fa2_334f300f90fb.ssng", 
    "updated_at": "2016-06-08T22:37:20-04:00", 
    "share_url": "https://a.sso.ng/1/334f300f90fb", 
    "audio_url": "https://s02.sso.ng/1/000000043fa2_334f300f90fb.m4a", 
    "comment_count": 0, 
    "timeline_image_url": "https://s02.sso.ng/1/000000043fa2_334f300f90fb_mr.jpg", 
    "song_album": "BTR", 
    "user": {
        "username": "Kait", 
        "verified": false, 
        "username_color": "#084e8c", 
        "full_name": "Jai's_main_squeeze", 
        "public_shuttersong": true, 
        "picture_thumb_url": "https://s02.sso.ng/users/3ef65736-6cc2-4fe4-9f0a-8244da25885f.jpg", 
        "id": "3ef65736-6cc2-4fe4-9f0a-8244da25885f"
    }, 
    "song_title": "Worldwide", 
    "is_mine": false, 
    "thumb_url": "https://s02.sso.ng/1/000000043fa2_334f300f90fb_th.jpg", 
    "song_artist": "Big Time Rush", 
    "favorite_count": 3, 
    "uuid": "FBE1E762-C226-472E-AFA1-F0273729F0EE"
}