{
    "mood": null, 
    "caption": "Este a\u00f1o me propuse mis metas 2016 #marialeregalauniphone", 
    "created_at": "2016-01-02T04:39:04-05:00", 
    "file_url": "https://s01.sso.ng/1/00000003bbe1_b7be2831835b.ssng", 
    "updated_at": "2016-01-02T21:27:26-05:00", 
    "share_url": "https://a.sso.ng/1/b7be2831835b", 
    "audio_url": "https://s01.sso.ng/1/00000003bbe1_b7be2831835b.m4a", 
    "comment_count": 0, 
    "timeline_image_url": "https://s01.sso.ng/1/00000003bbe1_b7be2831835b_mr.jpg", 
    "song_album": "", 
    "user": {
        "username": "stevenfigue", 
        "verified": false, 
        "username_color": null, 
        "full_name": null, 
        "public_shuttersong": true, 
        "picture_thumb_url": "https://s02.sso.ng/users/c7c7af50-cd41-4e89-8916-679253cf92c2.jpg", 
        "id": "c7c7af50-cd41-4e89-8916-679253cf92c2"
    }, 
    "song_title": "Beyonc - Halo", 
    "is_mine": false, 
    "thumb_url": "https://s01.sso.ng/1/00000003bbe1_b7be2831835b_th.jpg", 
    "song_artist": "", 
    "favorite_count": 1, 
    "uuid": "FD71D53D-091D-4AE9-9337-79A3D1CC13BA"
}