{
    "mood": null, 
    "caption": "#contest ? #jackandjack #jackjohnson #jackgilinksy #selfie #swimsuit #hot", 
    "created_at": "2015-08-05T17:12:53-04:00", 
    "file_url": "https://s01.sso.ng/1/000000022267_00b97aae23b5_1.ssng", 
    "updated_at": "2015-10-24T17:26:44-04:00", 
    "share_url": "https://a.sso.ng/1/00b97aae23b5", 
    "audio_url": "https://s01.sso.ng/1/000000022267_00b97aae23b5_1.m4a", 
    "comment_count": 0, 
    "timeline_image_url": "https://s01.sso.ng/1/000000022267_00b97aae23b5_1_mr.jpg", 
    "song_album": "Calibraska - EP", 
    "user": {
        "username": "alondrav12", 
        "verified": false, 
        "username_color": null, 
        "full_name": null, 
        "public_shuttersong": true, 
        "picture_thumb_url": "https://s02.sso.ng/users/", 
        "id": "b92c3aee-b3e0-440b-ab64-6daf7b49ab62"
    }, 
    "song_title": "Shallow Love", 
    "is_mine": false, 
    "thumb_url": "https://s01.sso.ng/1/000000022267_00b97aae23b5_1_th.jpg", 
    "song_artist": "Jack & Jack", 
    "favorite_count": 1, 
    "uuid": "FA7C61BE-C5AC-4FD2-869C-C5F4F1599B78"
}