{
    "mood": "shocked", 
    "caption": "one year ago today, June 28, 2015  I made the decision to go to an 8 hour concert with my best friend to see the two people who make my life worth it. and I have never missed an experience so much. time flies... and i hope to see & meet you soon \u2764\ufe0f #SOTS #2015", 
    "created_at": "2016-06-28T15:38:53-04:00", 
    "file_url": "https://s02.sso.ng/1/00000002094f_ccf4cc4b7127.ssng", 
    "updated_at": "2016-07-01T04:52:47-04:00", 
    "share_url": "https://a.sso.ng/1/ccf4cc4b7127", 
    "audio_url": "https://s02.sso.ng/1/00000002094f_ccf4cc4b7127.m4a", 
    "comment_count": 0, 
    "timeline_image_url": "https://s02.sso.ng/1/00000002094f_ccf4cc4b7127_mr.jpg", 
    "song_album": "Handwritten (Revisited)", 
    "user": {
        "username": "paige.scheirer", 
        "verified": false, 
        "username_color": "#28c4d8", 
        "full_name": "Jacks' Babe", 
        "public_shuttersong": true, 
        "picture_thumb_url": "https://s02.sso.ng/users/849f6e22-f8cc-4661-813b-77cc46769b27.jpg", 
        "id": "849f6e22-f8cc-4661-813b-77cc46769b27"
    }, 
    "song_title": "Memories", 
    "is_mine": false, 
    "thumb_url": "https://s02.sso.ng/1/00000002094f_ccf4cc4b7127_th.jpg", 
    "song_artist": "Shawn Mendes", 
    "favorite_count": 9, 
    "uuid": "F5F8D009-E2E9-4D9E-9F8D-865B6678BB86"
}